mavq/__init__.py
mavq/automationVariables.py
mavq/commonProvider.py
mavq/mavq.py
mavq/mavqAutomation.py
mavq/mavqPlatformClient.py
mavq/mavqUserContext.py
mavq_py-0.0.3.dist-info/LICENSE
mavq_py-0.0.3.dist-info/METADATA
mavq_py-0.0.3.dist-info/WHEEL
mavq_py-0.0.3.dist-info/top_level.txt
mavq_py-0.0.3.dist-info/RECORD
