Metadata-Version: 2.1
Name: mavq-py
Version: 0.0.3
Summary: A python client for mavQ platform
Home-page: https://mavq.com
Author: Parth Shah, Vishal Agrawal
Author-email: parth.t.shah@mavq.com, vishal.agarwal@mavq.com
Project-URL: Bug Tracker, https://github.com/pypa/sampleproject/issues
Classifier: Programming Language :: Python :: 3
Classifier: License :: OSI Approved :: MIT License
Classifier: Operating System :: OS Independent
Requires-Python: >=3.6
License-File: LICENSE
